MANIFEST.in
README.markdown
setup.py
pyblosxomsimplemarkdown/__init__.py
pyblosxomsimplemarkdown.egg-info/PKG-INFO
pyblosxomsimplemarkdown.egg-info/SOURCES.txt
pyblosxomsimplemarkdown.egg-info/dependency_links.txt
pyblosxomsimplemarkdown.egg-info/requires.txt
pyblosxomsimplemarkdown.egg-info/top_level.txt