Metadata-Version: 1.1
Name: pyblosxomsimplemarkdown
Version: 0.0.2
Summary: A Pyblosxom entryparser plugin that uses Markdown syntax and parses the whole file as the entry body
Home-page: https://github.com/seanh/pyblosxomsimplemarkdown
Author: Sean Hammond
Author-email: pyblosxomsimplemarkdown@seanh.cc
License: GPLv3
Keywords: pyblosxom
Platform: UNKNOWN
Classifier: Development Status :: 3 - Alpha
Classifier: License :: OSI Approved :: GNU General Public License v3 (GPLv3)
Classifier: Programming Language :: Python :: 2.7
